shelter/__init__.py
shelter/main.py
shelter/commands/__init__.py
shelter/commands/devserver.py
shelter/commands/runserver.py
shelter/commands/shell.py
shelter/commands/showconfig.py
shelter/commands/startproject.py
shelter/commands/startproject_skel/manage.py.template
shelter/commands/startproject_skel/setup.py.template
shelter/commands/startproject_skel/$package/__init__.py.template
shelter/commands/startproject_skel/$package/app.py.template
shelter/commands/startproject_skel/$package/commands.py.template
shelter/commands/startproject_skel/$package/config.py.template
shelter/commands/startproject_skel/$package/context.py.template
shelter/commands/startproject_skel/$package/handlers.py.template
shelter/commands/startproject_skel/$package/processes.py.template
shelter/commands/startproject_skel/$package/settings.py.template
shelter/commands/startproject_skel/$package/urls.py.template
shelter/contrib/__init__.py
shelter/contrib/swagger.py
shelter/contrib/config/__init__.py
shelter/contrib/config/iniconfig.py
shelter/core/__init__.py
shelter/core/app.py
shelter/core/cmdlineparser.py
shelter/core/commands.py
shelter/core/config.py
shelter/core/constants.py
shelter/core/context.py
shelter/core/exceptions.py
shelter/core/processes.py
shelter/core/web.py
shelter/utils/__init__.py
shelter/utils/imports.py
shelter/utils/net.py
shelter-2.4.0.dist-info/AUTHORS
shelter-2.4.0.dist-info/LICENSE
shelter-2.4.0.dist-info/METADATA
shelter-2.4.0.dist-info/WHEEL
shelter-2.4.0.dist-info/entry_points.txt
shelter-2.4.0.dist-info/top_level.txt
shelter-2.4.0.dist-info/RECORD
