Metadata-Version: 2.1
Name: shelter
Version: 2.4.0
Summary: Simple Python's Tornado wrapper which provides helpers for creationa new project, writing management commands, service processes, ...
Home-page: https://github.com/seznam/shelter
Author: Jan Seifert (Seznam.cz, a.s.)
Author-email: jan.seifert@firma.seznam.cz
License: BSD
Platform: any
Classifier: Programming Language :: Python :: 2.7
Classifier: Programming Language :: Python :: 3.4
Classifier: Programming Language :: Python :: 3.5
Classifier: Programming Language :: Python :: 3.6
Classifier: Programming Language :: Python :: 3.7
Classifier: License :: OSI Approved :: BSD License
Classifier: Operating System :: OS Independent
Classifier: Development Status :: 5 - Production/Stable
Classifier: Environment :: Web Environment
Classifier: Intended Audience :: Developers
Classifier: Topic :: Software Development :: Libraries :: Python Modules
License-File: LICENSE
License-File: AUTHORS
Requires-Dist: tornado (>=3.2)
Requires-Dist: six
Requires-Dist: setproctitle (>=1.1)
Provides-Extra: swagger
Requires-Dist: apispec ; extra == 'swagger'
Requires-Dist: apispec-webframeworks ; extra == 'swagger'
Requires-Dist: marshmallow ; extra == 'swagger'
Requires-Dist: swagger-ui-py ; extra == 'swagger'
